[
  {
    "model_config": "conv_vizdoom_recurrent.json",
    "env_config": "vizdoom_easy.json",
    "model_ext": "n_step3.json"
  },

  {
    "model_config": "conv_vizdoom_recurrent.json",
    "env_config": "vizdoom_easy.json",
    "model_ext": "n_step5.json"
  },

  {
    "model_config": "conv_vizdoom_recurrent.json",
    "env_config": "vizdoom_easy.json",
    "model_ext" : "her.json"
  },

  {
    "model_config": "conv_vizdoom_recurrent.json",
    "env_config": "vizdoom_easy.json",
    "model_ext" : "her_nstep3.json"
  },

  {
    "model_config": "conv_vizdoom_recurrent.json",
    "env_config": "vizdoom_easy.json",
    "model_ext" : "her_nstep5.json"
  }
]
